{
  "acacia_auriculiformis": {
    "scientific_name": "Acacia auriculiformis",
    "other_names": [
      "Auri"
    ]
  },
  "acacia_mangium": {
    "scientific_name": "Acacia mangium",
    "other_names": [
      "Mangium"
    ]
  },
  "acer_saccharum": {
    "scientific_name": "Acer saccharum",
    "other_names": [
      "Sugar Maple"
    ]
  },
  "dipterocarpus_grandiflorus": {
    "scientific_name": "Dipterocarpus grandiflorus",
    "other_names": [
      "Apitong"
    ]
  },
  "endospermum_peltatum": {
    "scientific_name": "Endospermum peltatum",
    "other_names": [
      "Gubas"
    ]
  },
  "eucalyptus_camaldulensis": {
    "scientific_name": "Eucalyptus camaldulensis",
    "other_names": [
      "River Red Gum "
    ]
  },
  "falcataria_falcata": {
    "scientific_name": "Falcataria falcata",
    "other_names": [
      "Moluccan Sau"
    ]
  },
  "fraxinus_americana": {
    "scientific_name": "Fraxinus americana",
    "other_names": [
      "Glacial Ash"
    ]
  },
  "gmelina_arborea": {
    "scientific_name": "Gmelina arborea",
    "other_names": [
      "Gmelina"
    ]
  },
  "hevea_brasiliensis": {
    "scientific_name": "Hevea brasiliensis",
    "other_names": [
      "Rubber"
    ]
  },
  "instia_bijuga": {
    "scientific_name": "Instia bijuga",
    "other_names": [
      "Ipil"
    ]
  },
  "juglans_nigra": {
    "scientific_name": "Juglans nigra",
    "other_names": [
      "Glacial Walnut "
    ]
  },
  "juglans_regia": {
    "scientific_name": "Juglans regia",
    "other_names": [
      "Walnut"
    ]
  },
  "leucaena_leucocephala": {
    "scientific_name": "Leucaena leucocephala",
    "other_names": [
      "Ipil-Ipil"
    ]
  },
  "palosapis": {
    "scientific_name": "Palosapis",
    "other_names": [
      "Palosapis"
    ]
  },
  "parashorea_malaanonan": {
    "scientific_name": "Parashorea malaanonan",
    "other_names": [
      "Bagtikan"
    ]
  },
  "pometia_pinnata": {
    "scientific_name": "Pometia pinnata",
    "other_names": [
      "Malugai"
    ]
  },
  "pterocarpus_indicus": {
    "scientific_name": "Pterocarpus indicus",
    "other_names": [
      "Narra"
    ]
  },
  "quercus_robur": {
    "scientific_name": "Quercus robur",
    "other_names": [
      "European Oak"
    ]
  },
  "samanea_saman": {
    "scientific_name": "Samanea saman",
    "other_names": [
      "Rain Tree"
    ]
  },
  "shorea_albida": {
    "scientific_name": "Shorea albida",
    "other_names": [
      "Dark Red Meranti"
    ]
  },
  "shorea_astylosa": {
    "scientific_name": "Shorea astylosa",
    "other_names": [
      "Yakal"
    ]
  },
  "shorea_contorta": {
    "scientific_name": "Shorea contorta",
    "other_names": [
      "White Lauan"
    ]
  },
  "shorea_negrosensis": {
    "scientific_name": "Shorea negrosensis",
    "other_names": [
      "Red Lauan"
    ]
  },
  "shorea_ovata": {
    "scientific_name": "Shorea ovata",
    "other_names": [
      "Tiaong"
    ]
  },
  "shorea_parvifolia": {
    "scientific_name": "Shorea parvifolia",
    "other_names": [
      "Light Red Meranti"
    ]
  },
  "shorea_polysperma": {
    "scientific_name": "Shorea polysperma",
    "other_names": [
      "Tanguile"
    ]
  },
  "swietenia_macrophylla": {
    "scientific_name": "Swietenia macrophylla",
    "other_names": [
      "Big-leafed mahogany"
    ]
  },
  "tectona_grandis": {
    "scientific_name": "Tectona grandis",
    "other_names": [
      "Teak"
    ]
  },
  "vitex_parviflora": {
    "scientific_name": "Vitex parviflora",
    "other_names": [
      "Molave"
    ]
  }
}